{
    "schemes": [
        "http",
        "https"
    ],
    "swagger": "2.0",
    "info": {
        "description": "API REST para reservas, servicios, combos y administracion de Atrevida Fit.",
        "title": "Atrevida Fit - Agenda API",
        "contact": {},
        "version": "v0.1"
    },
    "basePath": "/",
    "paths": {
        "/": {
            "get": {
                "description": "Devuelve un mensaje simple para confirmar que la API esta activa.",
                "produces": [
                    "application/json"
                ],
                "tags": [
                    "Base"
                ],
                "summary": "Estado de la API",
                "responses": {
                    "200": {
                        "description": "OK",
                        "schema": {
                            "$ref": "#/definitions/utils.APIResponse"
                        }
                    }
                }
            }
        },
        "/admin/importar": {
            "post": {
                "description": "Ejecuta la importacion de categorias, servicios y combos desde Google Sheets hacia PostgreSQL.",
                "produces": [
                    "application/json"
                ],
                "tags": [
                    "Admin"
                ],
                "summary": "Importar catalogo desde Google Sheets",
                "responses": {
                    "200": {
                        "description": "OK",
                        "schema": {
                            "$ref": "#/definitions/utils.APIResponse"
                        }
                    },
                    "500": {
                        "description": "Internal Server Error",
                        "schema": {
                            "$ref": "#/definitions/utils.APIResponse"
                        }
                    }
                }
            }
        },
        "/bd/categorias": {
            "get": {
                "description": "Devuelve todas las categorias registradas en la base de datos.",
                "produces": [
                    "application/json"
                ],
                "tags": [
                    "Categorias"
                ],
                "summary": "Listar categorias",
                "responses": {
                    "200": {
                        "description": "OK",
                        "schema": {
                            "$ref": "#/definitions/utils.APIResponse"
                        }
                    },
                    "500": {
                        "description": "Internal Server Error",
                        "schema": {
                            "$ref": "#/definitions/utils.APIResponse"
                        }
                    }
                }
            },
            "post": {
                "description": "Crea una nueva categoria en la base de datos.",
                "consumes": [
                    "application/json"
                ],
                "produces": [
                    "application/json"
                ],
                "tags": [
                    "Categorias"
                ],
                "summary": "Crear categoria",
                "parameters": [
                    {
                        "description": "Datos de la categoria",
                        "name": "payload",
                        "in": "body",
                        "required": true,
                        "schema": {
                            "$ref": "#/definitions/handlers.crearCategoriaRequest"
                        }
                    }
                ],
                "responses": {
                    "200": {
                        "description": "OK",
                        "schema": {
                            "$ref": "#/definitions/utils.APIResponse"
                        }
                    },
                    "400": {
                        "description": "Bad Request",
                        "schema": {
                            "$ref": "#/definitions/utils.APIResponse"
                        }
                    },
                    "500": {
                        "description": "Internal Server Error",
                        "schema": {
                            "$ref": "#/definitions/utils.APIResponse"
                        }
                    }
                }
            }
        },
        "/bd/clientes": {
            "get": {
                "description": "Devuelve clientes de PostgreSQL con filtros opcionales por nombre, apellido y numero de telefono.",
                "produces": [
                    "application/json"
                ],
                "tags": [
                    "Clientes"
                ],
                "summary": "Listar clientes",
                "parameters": [
                    {
                        "type": "string",
                        "description": "Busqueda parcial por nombre",
                        "name": "nombre",
                        "in": "query"
                    },
                    {
                        "type": "string",
                        "description": "Busqueda parcial por apellido",
                        "name": "apellido",
                        "in": "query"
                    },
                    {
                        "type": "string",
                        "description": "Busqueda parcial por numero de telefono",
                        "name": "numero_telefono",
                        "in": "query"
                    }
                ],
                "responses": {
                    "200": {
                        "description": "OK",
                        "schema": {
                            "$ref": "#/definitions/utils.APIResponse"
                        }
                    },
                    "500": {
                        "description": "Internal Server Error",
                        "schema": {
                            "$ref": "#/definitions/utils.APIResponse"
                        }
                    }
                }
            },
            "post": {
                "description": "Crea un nuevo cliente en la base de datos.",
                "consumes": [
                    "application/json"
                ],
                "produces": [
                    "application/json"
                ],
                "tags": [
                    "Clientes"
                ],
                "summary": "Crear cliente",
                "parameters": [
                    {
                        "description": "Datos del cliente",
                        "name": "payload",
                        "in": "body",
                        "required": true,
                        "schema": {
                            "$ref": "#/definitions/handlers.crearClienteRequest"
                        }
                    }
                ],
                "responses": {
                    "200": {
                        "description": "OK",
                        "schema": {
                            "$ref": "#/definitions/utils.APIResponse"
                        }
                    },
                    "400": {
                        "description": "Bad Request",
                        "schema": {
                            "$ref": "#/definitions/utils.APIResponse"
                        }
                    },
                    "409": {
                        "description": "Conflict",
                        "schema": {
                            "$ref": "#/definitions/utils.APIResponse"
                        }
                    },
                    "500": {
                        "description": "Internal Server Error",
                        "schema": {
                            "$ref": "#/definitions/utils.APIResponse"
                        }
                    }
                }
            }
        },
        "/bd/clientes/{id}": {
            "get": {
                "description": "Devuelve un cliente de PostgreSQL por su identificador.",
                "produces": [
                    "application/json"
                ],
                "tags": [
                    "Clientes"
                ],
                "summary": "Obtener cliente por ID",
                "parameters": [
                    {
                        "type": "integer",
                        "description": "ID del cliente",
                        "name": "id",
                        "in": "path",
                        "required": true
                    }
                ],
                "responses": {
                    "200": {
                        "description": "OK",
                        "schema": {
                            "$ref": "#/definitions/utils.APIResponse"
                        }
                    },
                    "400": {
                        "description": "Bad Request",
                        "schema": {
                            "$ref": "#/definitions/utils.APIResponse"
                        }
                    },
                    "404": {
                        "description": "Not Found",
                        "schema": {
                            "$ref": "#/definitions/utils.APIResponse"
                        }
                    },
                    "500": {
                        "description": "Internal Server Error",
                        "schema": {
                            "$ref": "#/definitions/utils.APIResponse"
                        }
                    }
                }
            },
            "delete": {
                "description": "Elimina un cliente de la base de datos.",
                "produces": [
                    "application/json"
                ],
                "tags": [
                    "Clientes"
                ],
                "summary": "Eliminar cliente",
                "parameters": [
                    {
                        "type": "integer",
                        "description": "ID del cliente",
                        "name": "id",
                        "in": "path",
                        "required": true
                    }
                ],
                "responses": {
                    "200": {
                        "description": "OK",
                        "schema": {
                            "$ref": "#/definitions/utils.APIResponse"
                        }
                    },
                    "400": {
                        "description": "Bad Request",
                        "schema": {
                            "$ref": "#/definitions/utils.APIResponse"
                        }
                    },
                    "404": {
                        "description": "Not Found",
                        "schema": {
                            "$ref": "#/definitions/utils.APIResponse"
                        }
                    },
                    "500": {
                        "description": "Internal Server Error",
                        "schema": {
                            "$ref": "#/definitions/utils.APIResponse"
                        }
                    }
                }
            },
            "patch": {
                "description": "Actualiza parcialmente un cliente existente en PostgreSQL.",
                "consumes": [
                    "application/json"
                ],
                "produces": [
                    "application/json"
                ],
                "tags": [
                    "Clientes"
                ],
                "summary": "Actualizar cliente",
                "parameters": [
                    {
                        "type": "integer",
                        "description": "ID del cliente",
                        "name": "id",
                        "in": "path",
                        "required": true
                    },
                    {
                        "description": "Campos a actualizar",
                        "name": "payload",
                        "in": "body",
                        "required": true,
                        "schema": {
                            "$ref": "#/definitions/handlers.actualizarClienteRequest"
                        }
                    }
                ],
                "responses": {
                    "200": {
                        "description": "OK",
                        "schema": {
                            "$ref": "#/definitions/utils.APIResponse"
                        }
                    },
                    "400": {
                        "description": "Bad Request",
                        "schema": {
                            "$ref": "#/definitions/utils.APIResponse"
                        }
                    },
                    "404": {
                        "description": "Not Found",
                        "schema": {
                            "$ref": "#/definitions/utils.APIResponse"
                        }
                    },
                    "409": {
                        "description": "Conflict",
                        "schema": {
                            "$ref": "#/definitions/utils.APIResponse"
                        }
                    },
                    "500": {
                        "description": "Internal Server Error",
                        "schema": {
                            "$ref": "#/definitions/utils.APIResponse"
                        }
                    }
                }
            }
        },
        "/bd/combos": {
            "get": {
                "description": "Devuelve combos persistidos en PostgreSQL con filtros opcionales.",
                "produces": [
                    "application/json"
                ],
                "tags": [
                    "Combos BD"
                ],
                "summary": "Listar combos desde base de datos",
                "parameters": [
                    {
                        "type": "string",
                        "description": "Busqueda parcial por nombre",
                        "name": "nombre",
                        "in": "query"
                    },
                    {
                        "type": "string",
                        "description": "Busqueda parcial por categoria",
                        "name": "categoria",
                        "in": "query"
                    },
                    {
                        "enum": [
                            "SAN MARTIN",
                            "PASEO ARANJUEZ"
                        ],
                        "type": "string",
                        "description": "Local",
                        "name": "local",
                        "in": "query"
                    },
                    {
                        "type": "integer",
                        "description": "Numero exacto de sesiones",
                        "name": "sesiones",
                        "in": "query"
                    }
                ],
                "responses": {
                    "200": {
                        "description": "OK",
                        "schema": {
                            "$ref": "#/definitions/utils.APIResponse"
                        }
                    },
                    "400": {
                        "description": "Bad Request",
                        "schema": {
                            "$ref": "#/definitions/utils.APIResponse"
                        }
                    }
                }
            }
        },
        "/bd/locales": {
            "get": {
                "description": "Devuelve todos los locales registrados en la base de datos.",
                "produces": [
                    "application/json"
                ],
                "tags": [
                    "Locales"
                ],
                "summary": "Listar locales",
                "responses": {
                    "200": {
                        "description": "OK",
                        "schema": {
                            "$ref": "#/definitions/utils.APIResponse"
                        }
                    },
                    "500": {
                        "description": "Internal Server Error",
                        "schema": {
                            "$ref": "#/definitions/utils.APIResponse"
                        }
                    }
                }
            },
            "post": {
                "description": "Crea un local y opcionalmente sus espacios asociados.",
                "consumes": [
                    "application/json"
                ],
                "produces": [
                    "application/json"
                ],
                "tags": [
                    "Locales"
                ],
                "summary": "Crear local",
                "parameters": [
                    {
                        "description": "Datos del local",
                        "name": "payload",
                        "in": "body",
                        "required": true,
                        "schema": {
                            "$ref": "#/definitions/handlers.crearLocalRequest"
                        }
                    }
                ],
                "responses": {
                    "200": {
                        "description": "OK",
                        "schema": {
                            "$ref": "#/definitions/utils.APIResponse"
                        }
                    },
                    "400": {
                        "description": "Bad Request",
                        "schema": {
                            "$ref": "#/definitions/utils.APIResponse"
                        }
                    },
                    "500": {
                        "description": "Internal Server Error",
                        "schema": {
                            "$ref": "#/definitions/utils.APIResponse"
                        }
                    }
                }
            }
        },
        "/bd/locales/{id}": {
            "get": {
                "description": "Devuelve un local de PostgreSQL por su identificador.",
                "produces": [
                    "application/json"
                ],
                "tags": [
                    "Locales"
                ],
                "summary": "Obtener local por ID",
                "parameters": [
                    {
                        "type": "integer",
                        "description": "ID del local",
                        "name": "id",
                        "in": "path",
                        "required": true
                    }
                ],
                "responses": {
                    "200": {
                        "description": "OK",
                        "schema": {
                            "$ref": "#/definitions/utils.APIResponse"
                        }
                    },
                    "400": {
                        "description": "Bad Request",
                        "schema": {
                            "$ref": "#/definitions/utils.APIResponse"
                        }
                    },
                    "500": {
                        "description": "Internal Server Error",
                        "schema": {
                            "$ref": "#/definitions/utils.APIResponse"
                        }
                    }
                }
            },
            "delete": {
                "description": "Realiza el borrado logico de un local estableciendo activo en false.",
                "produces": [
                    "application/json"
                ],
                "tags": [
                    "Locales"
                ],
                "summary": "Eliminar local",
                "parameters": [
                    {
                        "type": "integer",
                        "description": "ID del local",
                        "name": "id",
                        "in": "path",
                        "required": true
                    }
                ],
                "responses": {
                    "200": {
                        "description": "OK",
                        "schema": {
                            "$ref": "#/definitions/utils.APIResponse"
                        }
                    },
                    "400": {
                        "description": "Bad Request",
                        "schema": {
                            "$ref": "#/definitions/utils.APIResponse"
                        }
                    },
                    "404": {
                        "description": "Not Found",
                        "schema": {
                            "$ref": "#/definitions/utils.APIResponse"
                        }
                    },
                    "500": {
                        "description": "Internal Server Error",
                        "schema": {
                            "$ref": "#/definitions/utils.APIResponse"
                        }
                    }
                }
            },
            "patch": {
                "description": "Actualiza nombre o estado activo de un local existente.",
                "consumes": [
                    "application/json"
                ],
                "produces": [
                    "application/json"
                ],
                "tags": [
                    "Locales"
                ],
                "summary": "Actualizar local",
                "parameters": [
                    {
                        "type": "integer",
                        "description": "ID del local",
                        "name": "id",
                        "in": "path",
                        "required": true
                    },
                    {
                        "description": "Campos a actualizar",
                        "name": "payload",
                        "in": "body",
                        "required": true,
                        "schema": {
                            "$ref": "#/definitions/handlers.actualizarLocalRequest"
                        }
                    }
                ],
                "responses": {
                    "200": {
                        "description": "OK",
                        "schema": {
                            "$ref": "#/definitions/utils.APIResponse"
                        }
                    },
                    "400": {
                        "description": "Bad Request",
                        "schema": {
                            "$ref": "#/definitions/utils.APIResponse"
                        }
                    },
                    "404": {
                        "description": "Not Found",
                        "schema": {
                            "$ref": "#/definitions/utils.APIResponse"
                        }
                    },
                    "500": {
                        "description": "Internal Server Error",
                        "schema": {
                            "$ref": "#/definitions/utils.APIResponse"
                        }
                    }
                }
            }
        },
        "/bd/reservas": {
            "get": {
                "description": "Devuelve reservas desde PostgreSQL en formato simple y sin agrupacion por local.",
                "produces": [
                    "application/json"
                ],
                "tags": [
                    "Reservas BD"
                ],
                "summary": "Listar reservas simples",
                "parameters": [
                    {
                        "type": "string",
                        "description": "Nombre del local",
                        "name": "local",
                        "in": "query"
                    },
                    {
                        "type": "string",
                        "description": "Fecha exacta",
                        "name": "fecha",
                        "in": "query"
                    },
                    {
                        "type": "string",
                        "description": "Fecha desde",
                        "name": "fecha_desde",
                        "in": "query"
                    },
                    {
                        "type": "string",
                        "description": "Fecha hasta",
                        "name": "fecha_hasta",
                        "in": "query"
                    },
                    {
                        "type": "string",
                        "description": "Nombre del cliente",
                        "name": "cliente",
                        "in": "query"
                    },
                    {
                        "type": "string",
                        "description": "Numero de telefono",
                        "name": "numero_telefono",
                        "in": "query"
                    },
                    {
                        "type": "string",
                        "description": "Busqueda parcial por servicio solicitado",
                        "name": "servicio_solicitado",
                        "in": "query"
                    },
                    {
                        "type": "string",
                        "description": "Busqueda parcial por servicio confirmado",
                        "name": "servicio_confirmado",
                        "in": "query"
                    },
                    {
                        "enum": [
                            "PENDIENTE",
                            "RECHAZADO",
                            "AGENDADO",
                            "COMPLETADO"
                        ],
                        "type": "string",
                        "description": "Estado de la reserva",
                        "name": "estado",
                        "in": "query"
                    },
                    {
                        "enum": [
                            "mesa",
                            "bicicleta"
                        ],
                        "type": "string",
                        "description": "Tipo de reserva",
                        "name": "tipo",
                        "in": "query"
                    }
                ],
                "responses": {
                    "200": {
                        "description": "OK",
                        "schema": {
                            "$ref": "#/definitions/utils.APIResponse"
                        }
                    },
                    "400": {
                        "description": "Bad Request",
                        "schema": {
                            "$ref": "#/definitions/utils.APIResponse"
                        }
                    },
                    "500": {
                        "description": "Internal Server Error",
                        "schema": {
                            "$ref": "#/definitions/utils.APIResponse"
                        }
                    }
                }
            },
            "post": {
                "description": "Crea una reserva persistida en PostgreSQL.",
                "consumes": [
                    "application/json"
                ],
                "produces": [
                    "application/json"
                ],
                "tags": [
                    "Reservas BD"
                ],
                "summary": "Crear reserva en base de datos",
                "parameters": [
                    {
                        "description": "Datos de la reserva",
                        "name": "payload",
                        "in": "body",
                        "required": true,
                        "schema": {
                            "$ref": "#/definitions/handlers.crearReservaPGRequest"
                        }
                    }
                ],
                "responses": {
                    "201": {
                        "description": "Created",
                        "schema": {
                            "$ref": "#/definitions/utils.APIResponse"
                        }
                    },
                    "400": {
                        "description": "Bad Request",
                        "schema": {
                            "$ref": "#/definitions/utils.APIResponse"
                        }
                    },
                    "409": {
                        "description": "Conflict",
                        "schema": {
                            "$ref": "#/definitions/utils.APIResponse"
                        }
                    },
                    "500": {
                        "description": "Internal Server Error",
                        "schema": {
                            "$ref": "#/definitions/utils.APIResponse"
                        }
                    }
                }
            },
            "patch": {
                "description": "Actualiza una reserva existente en PostgreSQL.",
                "consumes": [
                    "application/json"
                ],
                "produces": [
                    "application/json"
                ],
                "tags": [
                    "Reservas BD"
                ],
                "summary": "Actualizar reserva en base de datos",
                "parameters": [
                    {
                        "description": "Datos para actualizar la reserva",
                        "name": "payload",
                        "in": "body",
                        "required": true,
                        "schema": {
                            "$ref": "#/definitions/handlers.actualizarReservaPGRequest"
                        }
                    }
                ],
                "responses": {
                    "200": {
                        "description": "OK",
                        "schema": {
                            "$ref": "#/definitions/utils.APIResponse"
                        }
                    },
                    "400": {
                        "description": "Bad Request",
                        "schema": {
                            "$ref": "#/definitions/utils.APIResponse"
                        }
                    },
                    "404": {
                        "description": "Not Found",
                        "schema": {
                            "$ref": "#/definitions/utils.APIResponse"
                        }
                    },
                    "500": {
                        "description": "Internal Server Error",
                        "schema": {
                            "$ref": "#/definitions/utils.APIResponse"
                        }
                    }
                }
            }
        },
        "/bd/reservas/calendario": {
            "get": {
                "description": "Devuelve reservas agrupadas por local con filtros opcionales.",
                "produces": [
                    "application/json"
                ],
                "tags": [
                    "Reservas BD"
                ],
                "summary": "Listar reservas desde base de datos",
                "parameters": [
                    {
                        "type": "string",
                        "description": "Nombre del local",
                        "name": "local",
                        "in": "query"
                    },
                    {
                        "type": "string",
                        "description": "Fecha exacta",
                        "name": "fecha",
                        "in": "query"
                    },
                    {
                        "type": "string",
                        "description": "Fecha desde",
                        "name": "fecha_desde",
                        "in": "query"
                    },
                    {
                        "type": "string",
                        "description": "Fecha hasta",
                        "name": "fecha_hasta",
                        "in": "query"
                    },
                    {
                        "type": "string",
                        "description": "Nombre del cliente",
                        "name": "cliente",
                        "in": "query"
                    },
                    {
                        "type": "string",
                        "description": "Numero de telefono",
                        "name": "numero_telefono",
                        "in": "query"
                    },
                    {
                        "type": "string",
                        "description": "Busqueda parcial por servicio solicitado",
                        "name": "servicio_solicitado",
                        "in": "query"
                    },
                    {
                        "type": "string",
                        "description": "Busqueda parcial por servicio confirmado",
                        "name": "servicio_confirmado",
                        "in": "query"
                    },
                    {
                        "enum": [
                            "PENDIENTE",
                            "RECHAZADO",
                            "AGENDADO",
                            "COMPLETADO"
                        ],
                        "type": "string",
                        "description": "Estado de la reserva",
                        "name": "estado",
                        "in": "query"
                    },
                    {
                        "enum": [
                            "mesa",
                            "bicicleta"
                        ],
                        "type": "string",
                        "description": "Tipo de reserva",
                        "name": "tipo",
                        "in": "query"
                    },
                    {
                        "type": "boolean",
                        "description": "Filtrar por estado reservado",
                        "name": "reservados",
                        "in": "query"
                    }
                ],
                "responses": {
                    "200": {
                        "description": "OK",
                        "schema": {
                            "$ref": "#/definitions/utils.APIResponse"
                        }
                    },
                    "400": {
                        "description": "Bad Request",
                        "schema": {
                            "$ref": "#/definitions/utils.APIResponse"
                        }
                    },
                    "500": {
                        "description": "Internal Server Error",
                        "schema": {
                            "$ref": "#/definitions/utils.APIResponse"
                        }
                    }
                }
            }
        },
        "/bd/reservas/estado": {
            "patch": {
                "description": "Cambia el estado de una reserva segun las reglas de negocio.",
                "consumes": [
                    "application/json"
                ],
                "produces": [
                    "application/json"
                ],
                "tags": [
                    "Reservas BD"
                ],
                "summary": "Actualizar estado de reserva",
                "parameters": [
                    {
                        "description": "Nuevo estado de la reserva",
                        "name": "payload",
                        "in": "body",
                        "required": true,
                        "schema": {
                            "$ref": "#/definitions/handlers.actualizarEstadoReservaPGRequest"
                        }
                    }
                ],
                "responses": {
                    "200": {
                        "description": "OK",
                        "schema": {
                            "$ref": "#/definitions/utils.APIResponse"
                        }
                    },
                    "400": {
                        "description": "Bad Request",
                        "schema": {
                            "$ref": "#/definitions/utils.APIResponse"
                        }
                    },
                    "404": {
                        "description": "Not Found",
                        "schema": {
                            "$ref": "#/definitions/utils.APIResponse"
                        }
                    },
                    "500": {
                        "description": "Internal Server Error",
                        "schema": {
                            "$ref": "#/definitions/utils.APIResponse"
                        }
                    }
                }
            }
        },
        "/bd/reservas/resumen": {
            "get": {
                "description": "Devuelve el resumen numerico de reservas agendadas del dia, servicios completados del dia y acumulado semanal desde el lunes hasta la fecha indicada.",
                "produces": [
                    "application/json"
                ],
                "tags": [
                    "Reservas BD"
                ],
                "summary": "Obtener resumen numerico de reservas",
                "parameters": [
                    {
                        "type": "string",
                        "description": "Fecha a consultar en formato YYYY-MM-DD",
                        "name": "fecha",
                        "in": "query",
                        "required": true
                    }
                ],
                "responses": {
                    "200": {
                        "description": "OK",
                        "schema": {
                            "allOf": [
                                {
                                    "$ref": "#/definitions/utils.APIResponse"
                                },
                                {
                                    "type": "object",
                                    "properties": {
                                        "data": {
                                            "$ref": "#/definitions/handlers.reservaResumenResponse"
                                        }
                                    }
                                }
                            ]
                        }
                    },
                    "400": {
                        "description": "Bad Request",
                        "schema": {
                            "$ref": "#/definitions/utils.APIResponse"
                        }
                    },
                    "500": {
                        "description": "Internal Server Error",
                        "schema": {
                            "$ref": "#/definitions/utils.APIResponse"
                        }
                    }
                }
            }
        },
        "/bd/reservas/{id}": {
            "get": {
                "description": "Devuelve una reserva de PostgreSQL por su identificador.",
                "produces": [
                    "application/json"
                ],
                "tags": [
                    "Reservas BD"
                ],
                "summary": "Obtener reserva por ID",
                "parameters": [
                    {
                        "type": "integer",
                        "description": "ID de la reserva",
                        "name": "id",
                        "in": "path",
                        "required": true
                    }
                ],
                "responses": {
                    "200": {
                        "description": "OK",
                        "schema": {
                            "$ref": "#/definitions/utils.APIResponse"
                        }
                    },
                    "400": {
                        "description": "Bad Request",
                        "schema": {
                            "$ref": "#/definitions/utils.APIResponse"
                        }
                    },
                    "404": {
                        "description": "Not Found",
                        "schema": {
                            "$ref": "#/definitions/utils.APIResponse"
                        }
                    },
                    "500": {
                        "description": "Internal Server Error",
                        "schema": {
                            "$ref": "#/definitions/utils.APIResponse"
                        }
                    }
                }
            },
            "delete": {
                "description": "Realiza el borrado logico de una reserva estableciendo activo en false.",
                "produces": [
                    "application/json"
                ],
                "tags": [
                    "Reservas BD"
                ],
                "summary": "Eliminar reserva",
                "parameters": [
                    {
                        "type": "integer",
                        "description": "ID de la reserva",
                        "name": "id",
                        "in": "path",
                        "required": true
                    }
                ],
                "responses": {
                    "200": {
                        "description": "OK",
                        "schema": {
                            "$ref": "#/definitions/utils.APIResponse"
                        }
                    },
                    "400": {
                        "description": "Bad Request",
                        "schema": {
                            "$ref": "#/definitions/utils.APIResponse"
                        }
                    },
                    "404": {
                        "description": "Not Found",
                        "schema": {
                            "$ref": "#/definitions/utils.APIResponse"
                        }
                    },
                    "500": {
                        "description": "Internal Server Error",
                        "schema": {
                            "$ref": "#/definitions/utils.APIResponse"
                        }
                    }
                }
            }
        },
        "/bd/servicios": {
            "get": {
                "description": "Devuelve servicios persistidos en PostgreSQL con filtros opcionales.",
                "produces": [
                    "application/json"
                ],
                "tags": [
                    "Servicios BD"
                ],
                "summary": "Listar servicios desde base de datos",
                "parameters": [
                    {
                        "type": "string",
                        "description": "Busqueda parcial por nombre",
                        "name": "nombre",
                        "in": "query"
                    },
                    {
                        "type": "string",
                        "description": "Busqueda parcial por categoria",
                        "name": "categoria",
                        "in": "query"
                    },
                    {
                        "enum": [
                            "SAN MARTIN",
                            "PASEO ARANJUEZ"
                        ],
                        "type": "string",
                        "description": "Local",
                        "name": "local",
                        "in": "query"
                    },
                    {
                        "type": "integer",
                        "description": "Numero exacto de sesiones",
                        "name": "sesiones",
                        "in": "query"
                    },
                    {
                        "type": "boolean",
                        "description": "Filtrar por servicios que requieren evaluacion",
                        "name": "requiere_evaluacion",
                        "in": "query"
                    }
                ],
                "responses": {
                    "200": {
                        "description": "OK",
                        "schema": {
                            "$ref": "#/definitions/utils.APIResponse"
                        }
                    },
                    "400": {
                        "description": "Bad Request",
                        "schema": {
                            "$ref": "#/definitions/utils.APIResponse"
                        }
                    }
                }
            },
            "post": {
                "description": "Crea un nuevo servicio en PostgreSQL y opcionalmente lo asocia a un local.",
                "consumes": [
                    "application/json"
                ],
                "produces": [
                    "application/json"
                ],
                "tags": [
                    "Servicios BD"
                ],
                "summary": "Crear servicio",
                "parameters": [
                    {
                        "description": "Datos del servicio",
                        "name": "payload",
                        "in": "body",
                        "required": true,
                        "schema": {
                            "$ref": "#/definitions/handlers.crearServicioRequest"
                        }
                    }
                ],
                "responses": {
                    "200": {
                        "description": "OK",
                        "schema": {
                            "$ref": "#/definitions/utils.APIResponse"
                        }
                    },
                    "400": {
                        "description": "Bad Request",
                        "schema": {
                            "$ref": "#/definitions/utils.APIResponse"
                        }
                    },
                    "500": {
                        "description": "Internal Server Error",
                        "schema": {
                            "$ref": "#/definitions/utils.APIResponse"
                        }
                    }
                }
            }
        },
        "/bd/servicios/local/{id}": {
            "post": {
                "description": "Asocia un servicio existente a un local determinado.",
                "consumes": [
                    "application/json"
                ],
                "produces": [
                    "application/json"
                ],
                "tags": [
                    "Servicios BD"
                ],
                "summary": "Activar servicio en local",
                "parameters": [
                    {
                        "type": "integer",
                        "description": "ID del servicio",
                        "name": "id",
                        "in": "path",
                        "required": true
                    },
                    {
                        "description": "Local donde activar el servicio",
                        "name": "payload",
                        "in": "body",
                        "required": true,
                        "schema": {
                            "$ref": "#/definitions/handlers.activarServicioRequest"
                        }
                    }
                ],
                "responses": {
                    "200": {
                        "description": "OK",
                        "schema": {
                            "$ref": "#/definitions/utils.APIResponse"
                        }
                    },
                    "400": {
                        "description": "Bad Request",
                        "schema": {
                            "$ref": "#/definitions/utils.APIResponse"
                        }
                    },
                    "500": {
                        "description": "Internal Server Error",
                        "schema": {
                            "$ref": "#/definitions/utils.APIResponse"
                        }
                    }
                }
            }
        },
        "/bd/servicios/{id}": {
            "get": {
                "description": "Devuelve un servicio de PostgreSQL por su identificador.",
                "produces": [
                    "application/json"
                ],
                "tags": [
                    "Servicios BD"
                ],
                "summary": "Obtener servicio por ID",
                "parameters": [
                    {
                        "type": "integer",
                        "description": "ID del servicio",
                        "name": "id",
                        "in": "path",
                        "required": true
                    }
                ],
                "responses": {
                    "200": {
                        "description": "OK",
                        "schema": {
                            "$ref": "#/definitions/utils.APIResponse"
                        }
                    },
                    "400": {
                        "description": "Bad Request",
                        "schema": {
                            "$ref": "#/definitions/utils.APIResponse"
                        }
                    },
                    "404": {
                        "description": "Not Found",
                        "schema": {
                            "$ref": "#/definitions/utils.APIResponse"
                        }
                    }
                }
            },
            "delete": {
                "description": "Realiza el borrado logico de un servicio estableciendo activo en false.",
                "produces": [
                    "application/json"
                ],
                "tags": [
                    "Servicios BD"
                ],
                "summary": "Eliminar servicio",
                "parameters": [
                    {
                        "type": "integer",
                        "description": "ID del servicio",
                        "name": "id",
                        "in": "path",
                        "required": true
                    }
                ],
                "responses": {
                    "200": {
                        "description": "OK",
                        "schema": {
                            "$ref": "#/definitions/utils.APIResponse"
                        }
                    },
                    "400": {
                        "description": "Bad Request",
                        "schema": {
                            "$ref": "#/definitions/utils.APIResponse"
                        }
                    },
                    "404": {
                        "description": "Not Found",
                        "schema": {
                            "$ref": "#/definitions/utils.APIResponse"
                        }
                    },
                    "500": {
                        "description": "Internal Server Error",
                        "schema": {
                            "$ref": "#/definitions/utils.APIResponse"
                        }
                    }
                }
            },
            "patch": {
                "description": "Actualiza un servicio existente en PostgreSQL.",
                "consumes": [
                    "application/json"
                ],
                "produces": [
                    "application/json"
                ],
                "tags": [
                    "Servicios BD"
                ],
                "summary": "Actualizar servicio",
                "parameters": [
                    {
                        "type": "integer",
                        "description": "ID del servicio",
                        "name": "id",
                        "in": "path",
                        "required": true
                    },
                    {
                        "description": "Campos a actualizar",
                        "name": "payload",
                        "in": "body",
                        "required": true,
                        "schema": {
                            "$ref": "#/definitions/handlers.actualizarServicioRequest"
                        }
                    }
                ],
                "responses": {
                    "200": {
                        "description": "OK",
                        "schema": {
                            "$ref": "#/definitions/utils.APIResponse"
                        }
                    },
                    "400": {
                        "description": "Bad Request",
                        "schema": {
                            "$ref": "#/definitions/utils.APIResponse"
                        }
                    },
                    "404": {
                        "description": "Not Found",
                        "schema": {
                            "$ref": "#/definitions/utils.APIResponse"
                        }
                    },
                    "500": {
                        "description": "Internal Server Error",
                        "schema": {
                            "$ref": "#/definitions/utils.APIResponse"
                        }
                    }
                }
            }
        },
        "/combos": {
            "get": {
                "description": "Devuelve combos filtrados por nombre, categoria, local y sesiones.",
                "produces": [
                    "application/json"
                ],
                "tags": [
                    "Catalogo"
                ],
                "summary": "Listar combos",
                "parameters": [
                    {
                        "type": "string",
                        "description": "Busqueda parcial por nombre",
                        "name": "nombre",
                        "in": "query"
                    },
                    {
                        "type": "string",
                        "description": "Busqueda parcial por categoria",
                        "name": "categoria",
                        "in": "query"
                    },
                    {
                        "enum": [
                            "ARANJUEZ",
                            "CENTRO",
                            "SAN MARTIN"
                        ],
                        "type": "string",
                        "description": "Local",
                        "name": "local",
                        "in": "query"
                    },
                    {
                        "type": "integer",
                        "description": "Numero exacto de sesiones",
                        "name": "sesiones",
                        "in": "query"
                    }
                ],
                "responses": {
                    "200": {
                        "description": "OK",
                        "schema": {
                            "$ref": "#/definitions/utils.APIResponse"
                        }
                    },
                    "400": {
                        "description": "Bad Request",
                        "schema": {
                            "$ref": "#/definitions/utils.APIResponse"
                        }
                    }
                }
            }
        },
        "/reservas": {
            "get": {
                "description": "Devuelve reservas filtradas por local, semana, dia, tipo, cliente y si estan reservadas.",
                "produces": [
                    "application/json"
                ],
                "tags": [
                    "Reservas Sheets"
                ],
                "summary": "Listar reservas desde Google Sheets",
                "parameters": [
                    {
                        "type": "string",
                        "description": "Nombre del local",
                        "name": "local",
                        "in": "query"
                    },
                    {
                        "type": "string",
                        "description": "Semana a consultar",
                        "name": "semana",
                        "in": "query"
                    },
                    {
                        "type": "string",
                        "description": "Dia a consultar",
                        "name": "dia",
                        "in": "query"
                    },
                    {
                        "enum": [
                            "mesa",
                            "bicicleta",
                            "feriado"
                        ],
                        "type": "string",
                        "description": "Tipo de reserva",
                        "name": "tipo",
                        "in": "query"
                    },
                    {
                        "type": "string",
                        "description": "Nombre del cliente",
                        "name": "cliente",
                        "in": "query"
                    },
                    {
                        "type": "boolean",
                        "description": "Filtrar solo reservados",
                        "name": "reservados",
                        "in": "query"
                    }
                ],
                "responses": {
                    "200": {
                        "description": "OK",
                        "schema": {
                            "$ref": "#/definitions/utils.APIResponse"
                        }
                    },
                    "400": {
                        "description": "Bad Request",
                        "schema": {
                            "$ref": "#/definitions/utils.APIResponse"
                        }
                    },
                    "500": {
                        "description": "Internal Server Error",
                        "schema": {
                            "$ref": "#/definitions/utils.APIResponse"
                        }
                    }
                }
            },
            "post": {
                "description": "Crea una reserva en uno o varios slots dentro de Google Sheets.",
                "consumes": [
                    "application/json"
                ],
                "produces": [
                    "application/json"
                ],
                "tags": [
                    "Reservas Sheets"
                ],
                "summary": "Crear reserva en Google Sheets",
                "parameters": [
                    {
                        "description": "Datos de la reserva",
                        "name": "payload",
                        "in": "body",
                        "required": true,
                        "schema": {
                            "$ref": "#/definitions/handlers.crearReservaRequest"
                        }
                    }
                ],
                "responses": {
                    "200": {
                        "description": "OK",
                        "schema": {
                            "$ref": "#/definitions/utils.APIResponse"
                        }
                    },
                    "207": {
                        "description": "Multi-Status",
                        "schema": {
                            "$ref": "#/definitions/utils.APIResponse"
                        }
                    },
                    "400": {
                        "description": "Bad Request",
                        "schema": {
                            "$ref": "#/definitions/utils.APIResponse"
                        }
                    },
                    "409": {
                        "description": "Conflict",
                        "schema": {
                            "$ref": "#/definitions/utils.APIResponse"
                        }
                    },
                    "500": {
                        "description": "Internal Server Error",
                        "schema": {
                            "$ref": "#/definitions/utils.APIResponse"
                        }
                    }
                }
            },
            "patch": {
                "description": "Modifica una reserva existente en Google Sheets.",
                "consumes": [
                    "application/json"
                ],
                "produces": [
                    "application/json"
                ],
                "tags": [
                    "Reservas Sheets"
                ],
                "summary": "Actualizar reserva en Google Sheets",
                "parameters": [
                    {
                        "description": "Datos para actualizar la reserva",
                        "name": "payload",
                        "in": "body",
                        "required": true,
                        "schema": {
                            "$ref": "#/definitions/handlers.actualizarReservaRequest"
                        }
                    }
                ],
                "responses": {
                    "200": {
                        "description": "OK",
                        "schema": {
                            "$ref": "#/definitions/utils.APIResponse"
                        }
                    },
                    "207": {
                        "description": "Multi-Status",
                        "schema": {
                            "$ref": "#/definitions/utils.APIResponse"
                        }
                    },
                    "400": {
                        "description": "Bad Request",
                        "schema": {
                            "$ref": "#/definitions/utils.APIResponse"
                        }
                    },
                    "409": {
                        "description": "Conflict",
                        "schema": {
                            "$ref": "#/definitions/utils.APIResponse"
                        }
                    },
                    "500": {
                        "description": "Internal Server Error",
                        "schema": {
                            "$ref": "#/definitions/utils.APIResponse"
                        }
                    }
                }
            }
        },
        "/reservas/celda-raw": {
            "get": {
                "description": "Obtiene la coordenada resuelta, el valor crudo y el parseo de una celda especifica.",
                "produces": [
                    "application/json"
                ],
                "tags": [
                    "Debug Sheets"
                ],
                "summary": "Ver contenido crudo de una celda",
                "parameters": [
                    {
                        "type": "string",
                        "description": "Local",
                        "name": "local",
                        "in": "query",
                        "required": true
                    },
                    {
                        "type": "string",
                        "description": "Semana",
                        "name": "semana",
                        "in": "query",
                        "required": true
                    },
                    {
                        "type": "string",
                        "description": "Dia",
                        "name": "dia",
                        "in": "query",
                        "required": true
                    },
                    {
                        "type": "string",
                        "description": "Hora",
                        "name": "hora",
                        "in": "query",
                        "required": true
                    }
                ],
                "responses": {
                    "200": {
                        "description": "OK",
                        "schema": {
                            "$ref": "#/definitions/utils.APIResponse"
                        }
                    },
                    "500": {
                        "description": "Internal Server Error",
                        "schema": {
                            "$ref": "#/definitions/utils.APIResponse"
                        }
                    }
                }
            }
        },
        "/reservas/raw": {
            "get": {
                "description": "Devuelve el contenido crudo de la hoja SAN MARTIN desde Google Sheets.",
                "produces": [
                    "application/json"
                ],
                "tags": [
                    "Debug Sheets"
                ],
                "summary": "Ver hoja cruda de reservas",
                "responses": {
                    "200": {
                        "description": "OK",
                        "schema": {
                            "type": "array",
                            "items": {}
                        }
                    }
                }
            }
        },
        "/reservas/unfiltered": {
            "get": {
                "description": "Devuelve todas las reservas procesadas desde Google Sheets sin aplicar filtros.",
                "produces": [
                    "application/json"
                ],
                "tags": [
                    "Debug Sheets"
                ],
                "summary": "Ver reservas sin filtrar",
                "responses": {
                    "200": {
                        "description": "OK",
                        "schema": {
                            "type": "array",
                            "items": {}
                        }
                    }
                }
            }
        },
        "/servicios": {
            "get": {
                "description": "Devuelve servicios filtrados por nombre, categoria, local y sesiones.",
                "produces": [
                    "application/json"
                ],
                "tags": [
                    "Catalogo"
                ],
                "summary": "Listar servicios",
                "parameters": [
                    {
                        "type": "string",
                        "description": "Busqueda parcial por nombre",
                        "name": "nombre",
                        "in": "query"
                    },
                    {
                        "type": "string",
                        "description": "Busqueda parcial por categoria",
                        "name": "categoria",
                        "in": "query"
                    },
                    {
                        "enum": [
                            "ARANJUEZ",
                            "CENTRO",
                            "SAN MARTIN"
                        ],
                        "type": "string",
                        "description": "Local",
                        "name": "local",
                        "in": "query"
                    },
                    {
                        "type": "integer",
                        "description": "Numero exacto de sesiones",
                        "name": "sesiones",
                        "in": "query"
                    },
                    {
                        "type": "boolean",
                        "description": "Filtrar por servicios que requieren evaluacion",
                        "name": "requiere_evaluacion",
                        "in": "query"
                    }
                ],
                "responses": {
                    "200": {
                        "description": "OK",
                        "schema": {
                            "$ref": "#/definitions/utils.APIResponse"
                        }
                    },
                    "400": {
                        "description": "Bad Request",
                        "schema": {
                            "$ref": "#/definitions/utils.APIResponse"
                        }
                    }
                }
            }
        },
        "/swagger/{any}": {
            "get": {
                "description": "Expone la interfaz web de Swagger para navegar la documentacion de la API.",
                "produces": [
                    "text/html"
                ],
                "tags": [
                    "Base"
                ],
                "summary": "Abrir Swagger UI",
                "responses": {
                    "200": {
                        "description": "Swagger UI",
                        "schema": {
                            "type": "string"
                        }
                    }
                }
            }
        }
    },
    "definitions": {
        "handlers.activarServicioRequest": {
            "type": "object",
            "required": [
                "local"
            ],
            "properties": {
                "local": {
                    "type": "string"
                }
            }
        },
        "handlers.actualizarClienteRequest": {
            "type": "object",
            "properties": {
                "apellido": {
                    "type": "string"
                },
                "nombre": {
                    "type": "string"
                },
                "numero_telefono": {
                    "type": "string"
                }
            }
        },
        "handlers.actualizarEstadoReservaPGRequest": {
            "type": "object",
            "required": [
                "estado",
                "id"
            ],
            "properties": {
                "causa": {
                    "type": "string"
                },
                "estado": {
                    "type": "string"
                },
                "id": {
                    "type": "integer"
                },
                "precio": {
                    "type": "number"
                },
                "servicio_confirmado": {
                    "type": "string"
                },
                "tipo": {
                    "type": "string"
                }
            }
        },
        "handlers.actualizarLocalRequest": {
            "type": "object",
            "properties": {
                "activo": {
                    "type": "boolean"
                },
                "nombre": {
                    "type": "string"
                }
            }
        },
        "handlers.actualizarReservaPGRequest": {
            "type": "object",
            "required": [
                "id",
                "local"
            ],
            "properties": {
                "id": {
                    "type": "integer"
                },
                "local": {
                    "type": "string"
                },
                "nueva_fecha": {
                    "type": "string"
                },
                "nueva_hora_desde": {
                    "type": "string"
                },
                "nueva_hora_hasta": {
                    "type": "string"
                },
                "nuevas_notas": {
                    "type": "string"
                },
                "nuevo_numero_telefono": {
                    "type": "string"
                },
                "nuevo_precio": {
                    "type": "number"
                },
                "nuevo_servicio": {
                    "type": "string"
                },
                "nuevo_servicio_confirmado": {
                    "type": "string"
                },
                "nuevo_servicio_solicitado": {
                    "type": "string"
                },
                "nuevo_tipo": {
                    "type": "string"
                }
            }
        },
        "handlers.actualizarReservaRequest": {
            "type": "object",
            "required": [
                "cliente",
                "dia",
                "hora",
                "local",
                "semana",
                "tipo"
            ],
            "properties": {
                "cliente": {
                    "type": "string"
                },
                "dia": {
                    "type": "string"
                },
                "hora": {
                    "type": "string"
                },
                "local": {
                    "type": "string"
                },
                "nueva_hora_desde": {
                    "type": "string"
                },
                "nueva_hora_hasta": {
                    "type": "string"
                },
                "nuevo_dia": {
                    "type": "string"
                },
                "nuevo_servicio": {
                    "type": "string"
                },
                "nuevo_tipo": {
                    "type": "string"
                },
                "semana": {
                    "type": "string"
                },
                "tipo": {
                    "type": "string"
                }
            }
        },
        "handlers.actualizarServicioRequest": {
            "type": "object",
            "properties": {
                "activo": {
                    "type": "boolean"
                },
                "categoria": {
                    "type": "string"
                },
                "costo": {
                    "type": "number"
                },
                "nombre": {
                    "type": "string"
                },
                "requiere_evaluacion": {
                    "type": "boolean"
                },
                "sesiones": {
                    "type": "integer"
                },
                "tiempo": {
                    "type": "string"
                },
                "tipo_espacio_requerido": {
                    "type": "string"
                }
            }
        },
        "handlers.crearCategoriaRequest": {
            "type": "object",
            "required": [
                "nombre"
            ],
            "properties": {
                "nombre": {
                    "type": "string"
                }
            }
        },
        "handlers.crearClienteRequest": {
            "type": "object",
            "properties": {
                "apellido": {
                    "type": "string"
                },
                "nombre": {
                    "type": "string"
                },
                "numero_telefono": {
                    "type": "string"
                }
            }
        },
        "handlers.crearLocalRequest": {
            "type": "object",
            "required": [
                "nombre"
            ],
            "properties": {
                "espacios": {
                    "description": "opcional",
                    "type": "array",
                    "items": {
                        "$ref": "#/definitions/handlers.espacioRequest"
                    }
                },
                "nombre": {
                    "type": "string"
                }
            }
        },
        "handlers.crearReservaPGRequest": {
            "type": "object",
            "required": [
                "cliente",
                "fecha",
                "hora_desde",
                "local",
                "numero_telefono"
            ],
            "properties": {
                "cliente": {
                    "type": "string"
                },
                "estado": {
                    "type": "string"
                },
                "fecha": {
                    "type": "string"
                },
                "hora_desde": {
                    "type": "string"
                },
                "hora_hasta": {
                    "type": "string"
                },
                "local": {
                    "type": "string"
                },
                "notas": {
                    "type": "string"
                },
                "numero_telefono": {
                    "type": "string"
                },
                "plan_id": {
                    "type": "integer"
                },
                "precio": {
                    "type": "number"
                },
                "servicio": {
                    "type": "string"
                },
                "servicio_confirmado": {
                    "type": "string"
                },
                "servicio_solicitado": {
                    "type": "string"
                },
                "tipo": {
                    "type": "string"
                }
            }
        },
        "handlers.crearReservaRequest": {
            "type": "object",
            "required": [
                "cliente",
                "dia",
                "hora_desde",
                "local",
                "semana",
                "tipo"
            ],
            "properties": {
                "cliente": {
                    "type": "string"
                },
                "dia": {
                    "type": "string"
                },
                "hora_desde": {
                    "type": "string"
                },
                "hora_hasta": {
                    "type": "string"
                },
                "local": {
                    "type": "string"
                },
                "semana": {
                    "type": "string"
                },
                "servicio": {
                    "type": "string"
                },
                "tipo": {
                    "type": "string"
                }
            }
        },
        "handlers.crearServicioRequest": {
            "type": "object",
            "required": [
                "categoria",
                "nombre"
            ],
            "properties": {
                "categoria": {
                    "type": "string"
                },
                "costo": {
                    "type": "number"
                },
                "local": {
                    "description": "opcional",
                    "type": "string"
                },
                "nombre": {
                    "type": "string"
                },
                "requiere_evaluacion": {
                    "type": "boolean"
                },
                "sesiones": {
                    "type": "integer"
                },
                "tiempo": {
                    "type": "string"
                },
                "tipo_espacio_requerido": {
                    "description": "\"M\" | \"B\" | nil",
                    "type": "string"
                }
            }
        },
        "handlers.espacioRequest": {
            "type": "object",
            "required": [
                "cantidad_espacios",
                "tipo_espacio"
            ],
            "properties": {
                "cantidad_espacios": {
                    "type": "integer",
                    "minimum": 1
                },
                "tipo_espacio": {
                    "type": "string"
                }
            }
        },
        "handlers.reservaResumenResponse": {
            "type": "object",
            "properties": {
                "reservas_agendadas_dia": {
                    "type": "integer"
                },
                "semana": {
                    "$ref": "#/definitions/handlers.reservaResumenSemanaResponse"
                },
                "servicios_completados_dia": {
                    "type": "integer"
                }
            }
        },
        "handlers.reservaResumenSemanaResponse": {
            "type": "object",
            "properties": {
                "jueves": {
                    "type": "integer"
                },
                "lunes": {
                    "type": "integer"
                },
                "martes": {
                    "type": "integer"
                },
                "miercoles": {
                    "type": "integer"
                },
                "sabado": {
                    "type": "integer"
                },
                "total_reservas": {
                    "type": "integer"
                },
                "viernes": {
                    "type": "integer"
                }
            }
        },
        "utils.APIResponse": {
            "type": "object",
            "properties": {
                "code": {
                    "type": "integer"
                },
                "data": {},
                "error": {
                    "type": "boolean"
                },
                "message": {
                    "type": "string"
                },
                "status": {
                    "type": "string"
                }
            }
        }
    }
}